ddtank/__init__.py
ddtank/status.py
ddtank/utils/__init__.py
ddtank/utils/aim.py
ddtank/utils/get_capture.py
ddtank/utils/get_game.py
ddtank/utils/get_map.py
ddtank/utils/get_script.py
ddtank/utils/stop_thread.py
ddtank-1.2.dist-info/LICENSE
ddtank-1.2.dist-info/METADATA
ddtank-1.2.dist-info/WHEEL
ddtank-1.2.dist-info/top_level.txt
ddtank-1.2.dist-info/RECORD
