Metadata-Version: 2.1
Name: ddtank
Version: 1.2
Summary: A package used for writing ddtank game scripts.
Author-email: zx <jugking6688@gmail.com>
Classifier: Programming Language :: Python :: 3
Classifier: License :: OSI Approved :: MIT License
Classifier: Operating System :: OS Independent
Requires-Python: >=3.8
License-File: LICENSE
Requires-Dist: pywin32 (==227)
Requires-Dist: onnxruntime (>=1.13.1)
Requires-Dist: ddtcv (==0.1.1)
Requires-Dist: pysimplegui (>=4.60.4)
